HamodyTools/HamodyTools.py
HamodyTools/__init__.py
HamodyTools-0.0.2.dist-info/METADATA
HamodyTools-0.0.2.dist-info/WHEEL
HamodyTools-0.0.2.dist-info/top_level.txt
HamodyTools-0.0.2.dist-info/RECORD
