Metadata-Version: 2.1
Name: HamodyTools
Version: 0.0.2
Summary: • Scrape Instagram Profile and login Instagram
Home-page: 
Author: Hamody
Author-email: 
Project-URL: Bug Tracker, https://github.com/pypa/sampleproject/issues
Classifier: Programming Language :: Python :: 3
Classifier: License :: OSI Approved :: MIT License
Classifier: Operating System :: OS Independent
Requires-Python: >=3.8
